03_ROrgPr/icarusVerilog/test.v
`ifndef __TEST_V__
`define __TEST_V__

module test(
	// output pins
	output wand x,
	output wor y,

	// input pins
	input a, b, c, d, e, f, g, h, i
	);

	// calculate x
	assign x = a;
	assign x = b;
	assign x = c;
	assign x = d;
	assign x = e;
	assign x = f;
	assign x = g;
	assign x = h;
	assign x = i;

	// calculate y
	assign y = a;
	assign y = b;
	assign y = c;
	assign y = d;
	assign y = e;
	assign y = f;
	assign y = g;
	assign y = h;
	assign y = i;

endmodule

`endif /* __TEST_V__ */

03_ROrgPr/icarusVerilog/testbench.v
`timescale 1ms/1ms

`include "test.v"

module testbench();

	reg a, b, c, d, e, f, g, h, i;
	wire x, y;

	test _test(
		.x(x),
		.y(y),

		.a(a), .b(b), .c(c),
		.d(d), .e(e), .f(f),
		.g(g), .h(h), .i(i)
	);

	initial begin
		// for simulation
		$dumpfile("test.vcd");
		$dumpvars(-1, _test);

		// initialize
		a <= 0; b <= 0; c <= 0;
		d <= 0; e <= 0; f <= 0;
		g <= 0; h <= 0; i <= 0;

		// start
		#1 a = 1;
		#1 b = 1;
		#1 c = 1;
		#1 d = 1;
		#1 e = 1;
		#1 f = 1;
		#1 g = 1;
		#1 h = 1;
		#1 i = 1;

		// end
		#1
		$finish;
	end

endmodule

03_ROrgPr/icarusVerilog/test.vcd
$date
	Thu Nov 03 05:20:02 2022
$end
$version
	Icarus Verilog
$end
$timescale
	1ms
$end
$scope module testbench $end
$scope module _test $end
$var wire 1 ! a $end
$var wire 1 " b $end
$var wire 1 # c $end
$var wire 1 $ d $end
$var wire 1 % e $end
$var wire 1 & f $end
$var wire 1 ' g $end
$var wire 1 ( h $end
$var wire 1 ) i $end
$var wire 1 * x $end
$var wire 1 + y $end
$upscope $end
$upscope $end
$enddefinitions $end
$comment Show the parameter values. $end
$dumpall
$end
#0
$dumpvars
0+
0*
0)
0(
0'
0&
0%
0$
0#
0"
0!
$end
#1
1+
1!
#2
1"
#3
1#
#4
1$
#5
1%
#6
1&
#7
1'
#8
1(
#9
1*
1)
