03_ROrgPr/Blatt02/Aufgabe02/mux2.vhd
library ieee;
use ieee.std_logic_1164.all;

-- Hier den Code einf?gen
entity mux2 is
	port (a : in std_logic;
		  b : in std_logic;
		  s : in std_logic;
		  y : out std_logic);
end mux2;

architecture behavioral of mux2 is
begin
	y <= (a and not s) or (b and s);
end behavioral;

03_ROrgPr/Blatt02/Aufgabe02/mux2_tb.vhd
library ieee;
use ieee.std_logic_1164.all;
use ieee.numeric_std.all;

entity mux2_tb is
end mux2_tb;

architecture behavioral of mux2_tb is
    constant NUM_TESTCASES : integer := 8;
	signal a_test : std_logic_vector(0 to NUM_TESTCASES - 1) := "0011XU11";
	signal b_test : std_logic_vector(0 to NUM_TESTCASES - 1) := "110000XU";
	signal sel_test : std_logic_vector(0 to NUM_TESTCASES - 1) := "01100110";
	signal y_ref : std_logic_vector(0 to NUM_TESTCASES - 1) := "0101X0X1";
	signal a,b,y,sel : std_logic;
	
begin

    MUX_INST: entity work.mux2(behavioral)
	port map(a => a, b => b,
	         s => sel, y => y);
	
    TESTBENCH: process
		variable numErrors : integer := 0;
    begin
        
        -- check if mux works correctly under common conditions
		for i in 0 to NUM_TESTCASES - 1 loop
			a <= a_test(i);
			b <= b_test(i);
			sel <= sel_test(i);

			wait for 5 ns;

			if y /= y_ref(i) then
                report "falsches Ergebnis am Multiplexer: " & std_logic'image(y) & " (erwartet: " & std_logic'image(y_ref(i)) & ")" severity error;
				numErrors := numErrors + 1;
			end if;

			wait for 5 ns;

		end loop;
        
        
        -- evaluation
        if numErrors = 0 then
	        report "Der Multiplexer funktioniert einwandfrei!" severity note;
	    else
	        report "Der Multiplexer funktioniert nicht einwandfrei! ("
	        & integer'image(numErrors) & " Fehler)" severity failure;
	    end if;
	    
	    wait;
    end process;

end behavioral;

03_ROrgPr/Blatt02/Aufgabe02/mux2.vcd
$date
  Tue Nov 15 07:41:09 2022
$end
$version
  GHDL v0
$end
$timescale
  1 fs
$end
$scope module standard $end
$upscope $end
$scope module std_logic_1164 $end
$upscope $end
$scope module numeric_std $end
$upscope $end
$scope module mux2_tb $end
$var reg 8 ! a_test[0:7] $end
$var reg 8 " b_test[0:7] $end
$var reg 8 # sel_test[0:7] $end
$var reg 8 $ y_ref[0:7] $end
$var reg 1 % a $end
$var reg 1 & b $end
$var reg 1 ' y $end
$var reg 1 ( sel $end
$scope module mux_inst $end
$var reg 1 ) a $end
$var reg 1 * b $end
$var reg 1 + s $end
$var reg 1 , y $end
$upscope $end
$upscope $end
$enddefinitions $end
#0
b0011XU11 !
b110000XU "
b01100110 #
b0101X0X1 $
0%
1&
0'
0(
0)
1*
0+
0,
#5000000
#10000000
1'
1(
1+
1,
#15000000
#20000000
1%
0&
0'
1)
0*
0,
#25000000
#30000000
1'
0(
0+
1,
#35000000
#40000000
X%
X'
X)
X,
#45000000
#50000000
U%
0'
1(
U)
1+
0,
#55000000
#60000000
1%
X&
X'
1)
X*
X,
#65000000
#70000000
U&
1'
0(
U*
0+
1,
